jungle/cli.py
jungle_test_cli-0.0.1.dist-info/METADATA
jungle_test_cli-0.0.1.dist-info/WHEEL
jungle_test_cli-0.0.1.dist-info/entry_points.txt
jungle_test_cli-0.0.1.dist-info/top_level.txt
jungle_test_cli-0.0.1.dist-info/RECORD
