Metadata-Version: 2.1
Name: jungle-test-cli
Version: 0.0.1
Summary: Jungle test CLI
Requires-Python: >=3.7
Requires-Dist: click
Requires-Dist: requests
Requires-Dist: pandas
